<instance description="" template="achievement">
	<group name="achievement_bag">
		<instance_reference name="reward_ribbon" value="ribbon\theater_of_war\scenarios\tow_sc_bonus_brody_i_need_no_help" />
		<int name="reward_xp" value="400" />
		<string name="steam_achievement_id" value="tow_bonus_brody_tank_war_i_need_no_help" />
		<list name="prerequisite_tasks">
			<template_reference name="task" value="achievement_task\scar">
				<int name="number" value="1" />
				<string name="task_id" value="tow_brody_tank_war_i_need_no_help" />
				<locstring name="name" value="0" />
			</template_reference>
		</list>
		<list name="prerequisite_achievements">
		</list>
	</group>
	<uniqueid name="pbgid" value="17430" />
</instance>