<instance description="Complete the Kalach Pincer scenario" template="ribbon">
	<group name="ribbon_bag">
		<locstring name="name" value="11052970" />
		<locstring name="description" value="11052973" />
		<icon name="icon" value="Icons_faceplate_medallions_faceplate_medallion_kharkovpincer_easy" />
		<bool name="is_medal" value="True" />
		<int name="priority" value="2300" />
		<icon name="icon_large" value="Icons_faceplate_rewards_rewards_kharkovpincer_easy" />
		<instance_reference name="achievement" value="" />
	</group>
	<uniqueid name="pbgid" value="2207" />
</instance>