<instance description="" template="skin_pack">
	<group name="skin_pack_bag">
		<icon name="icon" value="Icons_swatches_swatch_german_0008_summer_medium" />
		<enum name="kill_type" value="medium_armour" />
		<enum name="season" value="summer" />
		<instance_reference name="store_item" value="thq_store\skins\german\german_0008_summer_medium" />
		<template_reference name="server_item" value="server_item">
			<uniqueid name="server_id" value="396454" />
			<list name="search_tags">
				<locstring name="tag" value="11074085" />
				<locstring name="tag" value="11074008" />
			</list>
			<enum name="rarity" value="common" />
			<list name="races">
				<instance_reference name="race" value="racebps\german" />
			</list>
			<bool name="is_in_default_bundle" value="False" />
			<list name="default_metadata">
			</list>
			<instance_reference name="inventory_item_category" value="inventory_item_category\skin_pack\summer_medium" />
		</template_reference>
		<string name="skin_name" value="german_0008_summer" />
		<icon name="icon_secondary" value="Icons_swatches_preview_preview_german_0008_summer_medium" />
		<locstring name="name" value="11085051" />
		<locstring name="description" value="11046994" />
		<locstring name="description_short" value="11050444" />
	</group>
	<uniqueid name="pbgid" value="19575" />
</instance>