<instance description="" template="critical">
	<group name="critical_bag">
		<group name="critical_indicators">
			<enum name="indicator_01" value="vehicle_engine_yellow" />
			<enum name="indicator_02" value="" />
			<enum name="indicator_03" value="" />
		</group>
		<string name="description" value="yellow damage engine" />
		<bool name="is_unique" value="True" />
		<group name="kicker_message">
			<locstring name="message" value="2153900" />
			<float name="message_colour_a" value="255" />
			<float name="message_colour_b" value="0" />
			<float name="message_colour_g" value="0" />
			<float name="message_colour_r" value="255" />
			<float name="message_seconds" value="10" />
		</group>
		<enum name="target" value="tp_entity" />
		<list name="actions">
			<template_reference name="action" value="action\delay">
				<float name="delay" value="1" />
				<float name="delay_min" value="0" />
				<bool name="progress_bar" value="False" />
				<bool name="randomize" value="False" />
				<list name="delayed_actions">
					<template_reference name="action" value="action\apply_modifiers_action">
						<float name="duration" value="0" />
						<bool name="permanent" value="False" />
						<list name="modifiers">
							<template_reference name="modifier" value="modifiers\speed_maximum_modifier">
								<enum name="application_type" value="apply_to_entity" />
								<bool name="exclusive" value="True" />
								<string name="modifier_id" value="engine_damage" />
								<string name="target_type_name" value="" />
								<enum name="usage_type" value="multiplication" />
								<float name="value" value="0.4" />
								<instance_reference name="tooltip" value="modifier_tooltip\speed_maximum_modifier" />
							</template_reference>
							<template_reference name="modifier" value="modifiers\rotation_speed_modifier">
								<enum name="application_type" value="apply_to_entity" />
								<bool name="exclusive" value="True" />
								<string name="modifier_id" value="engine_damage" />
								<string name="target_type_name" value="" />
								<enum name="usage_type" value="multiplication" />
								<float name="value" value="0.6" />
								<instance_reference name="tooltip" value="modifier_tooltip\speed_maximum_modifier" />
							</template_reference>
						</list>
						<uniqueid name="id" value="53602" />
					</template_reference>
				</list>
				<uniqueid name="id" value="53601" />
				<bool name="can_prevent_refund" value="True" />
			</template_reference>
			<template_reference name="action" value="action\animator_set_state">
				<bool name="apply_to_leader_only" value="False" />
				<string name="do_action_state_name" value="Yellow" />
				<string name="state_machine_name" value="Criticals_Engine" />
				<string name="undo_action_state_name" value="Healthy" />
				<bool name="retrigger" value="False" />
				<uniqueid name="id" value="53603" />
			</template_reference>
		</list>
		<list name="requirements">
			<template_reference name="required" value="requirements\required_critical">
				<enum name="reason" value="usage" />
				<locstring name="ui_name" value="0" />
				<instance_reference name="critical_name" value="critical\vehicle_destroy_engine" />
				<bool name="is_present" value="False" />
			</template_reference>
		</list>
		<template_reference name="ui_info" value="tables\ui_info">
			<locstring name="screen_name" value="0" />
			<locstring name="help_text" value="11041997" />
			<string name="icon_name" value="Icons_criticals_temp_engine" />
			<string name="hotkey_name" value="" />
		</template_reference>
		<bool name="repairable" value="True" />
	</group>
	<uniqueid name="pbgid" value="61" />
</instance>